wdl_packager/__init__.py
wdl_packager/git.py
wdl_packager/utils.py
wdl_packager/version.py
wdl_packager/wdl_packager.py
wdl_packager-1.0.0.dist-info/LICENSE
wdl_packager-1.0.0.dist-info/METADATA
wdl_packager-1.0.0.dist-info/WHEEL
wdl_packager-1.0.0.dist-info/entry_points.txt
wdl_packager-1.0.0.dist-info/top_level.txt
wdl_packager-1.0.0.dist-info/RECORD
