Metadata-Version: 2.1
Name: wdl-packager
Version: 1.0.0
Summary: Package a WDL and its imports into a zip file.
Home-page: https://github.com/biowdl/wdl-packager
Author: Leiden University Medical Center
Author-email: sasc@lumc.nl
License: MIT
Keywords: WDL wdl zip package
Platform: UNKNOWN
Classifier: Programming Language :: Python :: 3 :: Only
Classifier: Programming Language :: Python :: 3
Classifier: Programming Language :: Python :: 3.6
Classifier: Programming Language :: Python :: 3.7
Classifier: Programming Language :: Python :: 3.8
Classifier: License :: OSI Approved :: MIT License
Requires-Python: >=3.6
Requires-Dist: miniwdl
